ntsvetanov_test_pypi/__init__.py
ntsvetanov_test_pypi/auth.py
ntsvetanov_test_pypi/main.py
ntsvetanov_test_pypi-0.0.3.dist-info/LICENSE
ntsvetanov_test_pypi-0.0.3.dist-info/METADATA
ntsvetanov_test_pypi-0.0.3.dist-info/WHEEL
ntsvetanov_test_pypi-0.0.3.dist-info/top_level.txt
ntsvetanov_test_pypi-0.0.3.dist-info/RECORD
