Metadata-Version: 2.1
Name: ntsvetanov-test-pypi
Version: 0.0.3
Summary: A small example package
Home-page: https://github.com/ntsvetanov/ntsvetanov_test_pypi
Author: ntsvetanov
Author-email: author@example.com
License: UNKNOWN
Platform: UNKNOWN
Classifier: Programming Language :: Python :: 3
Classifier: License :: OSI Approved :: MIT License
Classifier: Operating System :: OS Independent
Requires-Python: >=3.6
Requires-Dist: pandas
Provides-Extra: dev
Requires-Dist: pytest ; extra == 'dev'
Provides-Extra: google-auth
Requires-Dist: google-auth ; extra == 'google-auth'
Provides-Extra: jwt
Requires-Dist: pyjwt ; extra == 'jwt'
